<?xml version="1.0" encoding="utf-8" ?>
<dwsync>
<file name="index.php" server="192.185.27.241/public_html/" local="130878389260000000" remote="131038684800000000" Dst="0" />
<file name="revolution.extension.actions.min.js" server="192.185.27.241/public_html/" local="130929334720000000" remote="131038684800000000" Dst="0" />
<file name="revolution.extension.carousel.min.js" server="192.185.27.241/public_html/" local="130881793440000000" remote="131038684800000000" Dst="0" />
<file name="revolution.extension.kenburn.min.js" server="192.185.27.241/public_html/" local="130878389260000000" remote="131038684800000000" Dst="0" />
<file name="revolution.extension.layeranimation.min.js" server="192.185.27.241/public_html/" local="130930852800000000" remote="131038684800000000" Dst="0" />
<file name="revolution.extension.migration.min.js" server="192.185.27.241/public_html/" local="130878389260000000" remote="131038684800000000" Dst="0" />
<file name="revolution.extension.navigation.min.js" server="192.185.27.241/public_html/" local="130916382040000000" remote="131038684800000000" Dst="0" />
<file name="revolution.extension.parallax.min.js" server="192.185.27.241/public_html/" local="130930245660000000" remote="131038684800000000" Dst="0" />
<file name="revolution.extension.slideanims.min.js" server="192.185.27.241/public_html/" local="130916391460000000" remote="131038684800000000" Dst="0" />
<file name="revolution.extension.video.min.js" server="192.185.27.241/public_html/" local="130931027500000000" remote="131038684800000000" Dst="0" />
</dwsync>